CHANGELOG.md
LICENSE.txt
MANIFEST.in
README.md
setup.py
temps.py
temps.egg-info/PKG-INFO
temps.egg-info/SOURCES.txt
temps.egg-info/dependency_links.txt
temps.egg-info/top_level.txt