Metadata-Version: 1.1
Name: temps
Version: 0.3.0
Summary: Context managers for creating and cleaning up temporary directories and files.
Home-page: https://github.com/todddeluca/temps
Author: Todd Francis DeLuca
Author-email: todddeluca@yahoo.com
License: MIT
Keywords: python temporary files directories context manager
Platform: UNKNOWN
Classifier: License :: OSI Approved :: MIT License
Classifier: Development Status :: 3 - Alpha
Classifier: Programming Language :: Python :: 2
Classifier: Programming Language :: Python :: 2.7
